github3/__about__.py
github3/__init__.py
github3/api.py
github3/auths.py
github3/decorators.py
github3/events.py
github3/exceptions.py
github3/git.py
github3/github.py
github3/licenses.py
github3/models.py
github3/notifications.py
github3/orgs.py
github3/pulls.py
github3/session.py
github3/structs.py
github3/users.py
github3/utils.py
github3/gists/__init__.py
github3/gists/comment.py
github3/gists/file.py
github3/gists/gist.py
github3/gists/history.py
github3/issues/__init__.py
github3/issues/comment.py
github3/issues/event.py
github3/issues/issue.py
github3/issues/label.py
github3/issues/milestone.py
github3/repos/__init__.py
github3/repos/branch.py
github3/repos/comment.py
github3/repos/commit.py
github3/repos/comparison.py
github3/repos/contents.py
github3/repos/deployment.py
github3/repos/hook.py
github3/repos/issue_import.py
github3/repos/pages.py
github3/repos/release.py
github3/repos/repo.py
github3/repos/stats.py
github3/repos/status.py
github3/repos/tag.py
github3/search/__init__.py
github3/search/code.py
github3/search/issue.py
github3/search/repository.py
github3/search/user.py
sqre_github3.py-1.0.0a4.dist-info/DESCRIPTION.rst
sqre_github3.py-1.0.0a4.dist-info/METADATA
sqre_github3.py-1.0.0a4.dist-info/pydist.json
sqre_github3.py-1.0.0a4.dist-info/RECORD
sqre_github3.py-1.0.0a4.dist-info/top_level.txt
sqre_github3.py-1.0.0a4.dist-info/WHEEL
